[
{"inst_id":"AG0627","inst_name":"Association of overseas Chinese in Vietnam","inst_name_lang":"en","place":"SP0436","created":"2017-07-09","created_by":"OS","last_modified":"2020-04-02","last_modified_by":"DP"},
{"inst_id":"AG0627","inst_name":"越南华侨协会","inst_name_lang":"zh","place":"SP0436","created":"2017-07-09","created_by":"OS","last_modified":"2020-04-02","last_modified_by":"DP"}
,
{"inst_id":"AG0628","inst_name":"Beatles","inst_name_lang":"en","place":"SP0134","start":"1960","end":"1970","created":"2017-07-09","created_by":"OS","last_modified":"2020-04-02","last_modified_by":"DP"},
{"inst_id":"AG0629","inst_name":"English Language Services","inst_name_lang":"en","place":"SP0436","created":"2017-07-12","created_by":"OS","last_modified":"2020-04-02","last_modified_by":"DP"},
{"inst_id":"AG0630","inst_name":"Central Committee of the Communist Party in China","inst_name_lang":"en","place":"SP0005","start":"1921","created":"2017-12-23","created_by":"OS","last_modified":"2020-04-02","last_modified_by":"DP"},
{"inst_id":"AG0630","inst_name":"中国共产党中央委员会","inst_name_lang":"zh","place":"SP0005","start":"1921","alt_start":"1921","alt_end":"1922","inst_alt_name":"中国共产党中央局","created":"2018-02-05","created_by":"MG","last_modified":"2020-04-02","last_modified_by":"DP"}
,
{"inst_id":"AG0630","inst_name":"中国共产党中央执行委员会","inst_name_lang":"zh","place":"SP0005","start":"1922","end":"1927","alt_start":"1921","inst_alt_name":"中国共产党中央委员会","created":"2018-02-05","created_by":"MG","last_modified":"2020-04-02","last_modified_by":"DP"}
,
{"inst_id":"AG0631","inst_name":"Baiyangdian literary society","inst_name_lang":"en","place":"SP0025","start":"1968","end":"1976","created":"2018-01-30","created_by":"OS","last_modified":"2020-04-02","last_modified_by":"DP"},
{"inst_id":"AG0631","inst_name":"白洋淀派","inst_name_lang":"zh","place":"SP0025","start":"1968","end":"1976","created":"2018-01-30","created_by":"OS","last_modified":"2020-04-02","last_modified_by":"DP"}
,
{"inst_id":"AG0632","inst_name":"School of Foreign Studies","inst_name_lang":"en","place":"SP0093","start":"1917","alt_start":"1938","alt_end":"1993","inst_alt_name":"Department of Foreign Languages and Literatures","created":"2018-02-22","created_by":"MG","last_modified":"2020-04-02","last_modified_by":"DP"},
{"inst_id":"AG0633","inst_name":"Beijing No. 4 High School","inst_name_lang":"en","place":"SP0005","start":"1906","alt_start":"1911","alt_end":"1949","inst_alt_name":"Capital Public No. 4 Secondary School","created":"2018-02-22","created_by":"MG","last_modified":"2020-04-02","last_modified_by":"DP"},
{"inst_id":"AG0633","inst_name":"北京市第四中学","inst_name_lang":"zh","place":"SP0005","start":"1906","alt_start":"1911","alt_end":"1949","inst_alt_name":"京师公立第四中学","created":"2018-02-22","created_by":"MG","last_modified":"2020-04-02","last_modified_by":"DP"}
,
{"inst_id":"AG0634","inst_name":"The Communist Party of China","inst_name_lang":"en","place":"SP0005","start":"1921","created":"2018-03-21","created_by":"MG","last_modified":"2020-04-02","last_modified_by":"DP"},
{"inst_id":"AG0634","inst_name":"中国共产党","inst_name_lang":"zh","place":"SP0005","start":"1921","created":"2018-03-21","created_by":"MG","last_modified":"2020-04-02","last_modified_by":"DP"}
,
{"inst_id":"AG0635","inst_name":"Voice of America","inst_name_lang":"en","place":"SP0225","start":"1942","source":"https://www.voanews.com/","page":"ONLINE SOURCE","created":"2018-04-03","created_by":"MG","last_modified":"2020-04-02","last_modified_by":"DP"},
{"inst_id":"AG0636","inst_name":"August First Film Studio","inst_name_lang":"en","place":"SP0005","start":"1951","created":"2018-10-18","created_by":"WH","last_modified":"2020-04-02","last_modified_by":"DP"},
{"inst_id":"AG0636","inst_name":"八一电影制片厂","inst_name_lang":"zh","place":"SP0005","start":"1951","created":"2018-10-18","created_by":"WH","last_modified":"2020-04-02","last_modified_by":"DP"}
,
{"inst_id":"AG0637","inst_name":"Alexandrov Ensemble","inst_name_lang":"en","place":"SP0030","start":"1928","source":"https://ru.wikipedia.org/wiki/%D0%90%D0%BD%D1%81%D0%B0%D0%BC%D0%B1%D0%BB%D1%8C_%D0%BF%D0%B5%D1%81%D0%BD%D0%B8_%D0%B8_%D0%BF%D0%BB%D1%8F%D1%81%D0%BA%D0%B8_%D0%A0%D0%BE%D1%81%D1%81%D0%B8%D0%B9%D1%81%D0%BA%D0%BE%D0%B9_%D0%B0%D1%80%D0%BC%D0%B8%D0%B8_%D0%B8%D0%BC%D0%B5%D0%BD%D0%B8_%D0%90._%D0%92._%D0%90%D0%BB%D0%B5%D0%BA%D1%81%D0%B0%D0%BD%D0%B4%D1%80%D0%BE%D0%B2%D0%B0","created":"2018-11-04","created_by":"WH","last_modified":"2020-04-02","last_modified_by":"DP"},
{"inst_id":"AG0637","inst_name":"Ансамбль песни и пляски Российской армии имени А. В. Александрова","inst_name_lang":"ru","place":"SP0030","start":"1928","source":"https://ru.wikipedia.org/wiki/%D0%90%D0%BD%D1%81%D0%B0%D0%BC%D0%B1%D0%BB%D1%8C_%D0%BF%D0%B5%D1%81%D0%BD%D0%B8_%D0%B8_%D0%BF%D0%BB%D1%8F%D1%81%D0%BA%D0%B8_%D0%A0%D0%BE%D1%81%D1%81%D0%B8%D0%B9%D1%81%D0%BA%D0%BE%D0%B9_%D0%B0%D1%80%D0%BC%D0%B8%D0%B8_%D0%B8%D0%BC%D0%B5%D0%BD%D0%B8_%D0%90._%D0%92._%D0%90%D0%BB%D0%B5%D0%BA%D1%81%D0%B0%D0%BD%D0%B4%D1%80%D0%BE%D0%B2%D0%B0","created":"2018-11-04","created_by":"WH","last_modified":"2020-04-02","last_modified_by":"DP"}
,
{"inst_id":"AG0637","inst_name":"亚历山德罗夫红旗歌舞团","inst_name_lang":"zh","place":"SP0030","start":"1928","source":"https://ru.wikipedia.org/wiki/%D0%90%D0%BD%D1%81%D0%B0%D0%BC%D0%B1%D0%BB%D1%8C_%D0%BF%D0%B5%D1%81%D0%BD%D0%B8_%D0%B8_%D0%BF%D0%BB%D1%8F%D1%81%D0%BA%D0%B8_%D0%A0%D0%BE%D1%81%D1%81%D0%B8%D0%B9%D1%81%D0%BA%D0%BE%D0%B9_%D0%B0%D1%80%D0%BC%D0%B8%D0%B8_%D0%B8%D0%BC%D0%B5%D0%BD%D0%B8_%D0%90._%D0%92._%D0%90%D0%BB%D0%B5%D0%BA%D1%81%D0%B0%D0%BD%D0%B4%D1%80%D0%BE%D0%B2%D0%B0","created":"2018-11-04","created_by":"WH","last_modified":"2020-04-02","last_modified_by":"DP"}
,
{"inst_id":"AG0638","inst_name":"Hubei Opera and Dance Theatre","inst_name_lang":"en","place":"SP0340","start":"1952","alt_start":"1952","alt_end":"1998","inst_alt_name":"Hubei Experimental Opera Troupe","source":"https://baike.baidu.com/item/%E6%B9%96%E5%8C%97%E7%9C%81%E5%AE%9E%E9%AA%8C%E6%AD%8C%E5%89%A7%E5%9B%A2","created":"2018-11-04","created_by":"WH","last_modified":"2020-04-02","last_modified_by":"DP"},
{"inst_id":"AG0638","inst_name":"湖北省歌舞剧院","inst_name_lang":"zh","place":"SP0340","start":"1952","alt_start":"1952","alt_end":"1998","inst_alt_name":"湖北省实验歌剧团","source":"https://baike.baidu.com/item/%E6%B9%96%E5%8C%97%E7%9C%81%E5%AE%9E%E9%AA%8C%E6%AD%8C%E5%89%A7%E5%9B%A2","created":"2018-11-04","created_by":"WH","last_modified":"2020-04-02","last_modified_by":"DP"}
,
{"inst_id":"AG0639","inst_name":"Jin Opera Group of Liulin County, Shanxi Province","inst_name_lang":"en","place":"SP0341","source":"https://baike.baidu.com/item/%E4%B8%89%E4%B8%8A%E6%A1%83%E5%B3%B0","created":"2018-11-04","created_by":"WH","last_modified":"2020-04-02","last_modified_by":"DP"},
{"inst_id":"AG0639","inst_name":"山西省柳林县晋剧团","inst_name_lang":"zh","place":"SP0341","source":"https://baike.baidu.com/item/%E4%B8%89%E4%B8%8A%E6%A1%83%E5%B3%B0","created":"2018-11-04","created_by":"WH","last_modified":"2020-04-02","last_modified_by":"DP"}
,
{"inst_id":"AG0640","inst_name":"China Writers Association","inst_name_lang":"en","place":"SP0005","start":"1949","alt_start":"1949","alt_end":"1953","inst_alt_name":"Chinese National Literary Workers Association","source":"https://zh.wikipedia.org/wiki/%E4%B8%AD%E5%9B%BD%E4%BD%9C%E5%AE%B6%E5%8D%8F%E4%BC%9A","created":"2018-11-04","created_by":"WH","last_modified":"2020-04-02","last_modified_by":"DP"},
{"inst_id":"AG0640","inst_name":"中国作家协会","inst_name_lang":"zh","place":"SP0005","start":"1949","alt_start":"1949","alt_end":"1953","inst_alt_name":"中华全国文学工作者协会","source":"https://zh.wikipedia.org/wiki/%E4%B8%AD%E5%9B%BD%E4%BD%9C%E5%AE%B6%E5%8D%8F%E4%BC%9A","created":"2018-11-04","created_by":"WH","last_modified":"2020-04-02","last_modified_by":"DP"}
,
{"inst_id":"AG0641","inst_name":"Hunan Federation of Literary and Art Circles","inst_name_lang":"en","place":"SP0054","start":"1950","alt_end":"1950","inst_alt_name":"Changsha Federation of Literary and Art Circles","source":"https://baike.baidu.com/item/%E6%B9%96%E5%8D%97%E7%9C%81%E6%96%87%E5%AD%A6%E8%89%BA%E6%9C%AF%E7%95%8C%E8%81%94%E5%90%88%E4%BC%9A/2046912","created":"2018-11-04","created_by":"WH","last_modified":"2020-04-02","last_modified_by":"DP"},
{"inst_id":"AG0641","inst_name":"湖南省文学艺术界联合会","inst_name_lang":"zh","place":"SP0054","start":"1950","alt_end":"1950","inst_alt_name":"长沙市文学艺术界联合会","source":"https://baike.baidu.com/item/%E6%B9%96%E5%8D%97%E7%9C%81%E6%96%87%E5%AD%A6%E8%89%BA%E6%9C%AF%E7%95%8C%E8%81%94%E5%90%88%E4%BC%9A/2046912","created":"2018-11-04","created_by":"WH","last_modified":"2020-04-02","last_modified_by":"DP"}
,
{"inst_id":"AG0642","inst_name":"Jiangxi Jiujiang Cultural Work Group","inst_name_lang":"en","place":"SP0240","source":"W0431","created":"2018-11-06","created_by":"WH","last_modified":"2020-04-02","last_modified_by":"DP"},
{"inst_id":"AG0642","inst_name":"江西九江文工团","inst_name_lang":"zh","place":"SP0240","source":"W0431","created":"2018-11-06","created_by":"WH","last_modified":"2020-04-02","last_modified_by":"DP"}
,
{"inst_id":"AG0643","inst_name":"Shanghai Youth Art Theatre","inst_name_lang":"en","place":"SP0006","source":"https://zh.wikipedia.org/wiki/%E6%9D%9C%E9%B9%83%E5%B1%B1","created":"2018-11-06","created_by":"WH","last_modified":"2020-04-02","last_modified_by":"DP"},
{"inst_id":"AG0643","inst_name":"上海青年艺术剧院","inst_name_lang":"zh","place":"SP0006","source":"https://zh.wikipedia.org/wiki/%E6%9D%9C%E9%B9%83%E5%B1%B1","created":"2018-11-06","created_by":"WH","last_modified":"2020-04-02","last_modified_by":"DP"}
,
{"inst_id":"AG0644","inst_name":"Beijing Peking Opera Troupe","inst_name_lang":"en","place":"SP0005","start":"1955","source":"https://baike.baidu.com/item/%E5%8C%97%E4%BA%AC%E4%BA%AC%E5%89%A7%E5%9B%A2","created":"2018-11-06","created_by":"WH","last_modified":"2020-04-02","last_modified_by":"DP"},
{"inst_id":"AG0644","inst_name":"北京京剧团","inst_name_lang":"zh","place":"SP0005","start":"1955","source":"https://baike.baidu.com/item/%E5%8C%97%E4%BA%AC%E4%BA%AC%E5%89%A7%E5%9B%A2","created":"2018-11-06","created_by":"WH","last_modified":"2020-04-02","last_modified_by":"DP"}
,
{"inst_id":"AG0645","inst_name":"China Central Ballet Company","inst_name_lang":"en","place":"SP0005","start":"1959","source":"https://baike.baidu.com/item/%E4%B8%AD%E5%A4%AE%E8%8A%AD%E8%95%BE%E8%88%9E%E5%9B%A2#2_1","created":"2018-11-06","created_by":"WH","last_modified":"2020-04-02","last_modified_by":"DP"},
{"inst_id":"AG0645","inst_name":"中央芭蕾舞团","inst_name_lang":"zh","place":"SP0005","start":"1959","source":"https://baike.baidu.com/item/%E4%B8%AD%E5%A4%AE%E8%8A%AD%E8%95%BE%E8%88%9E%E5%9B%A2#2_1","created":"2018-11-06","created_by":"WH","last_modified":"2020-04-02","last_modified_by":"DP"}
,
{"inst_id":"AG0646","inst_name":"Hunan Opera and Dance Theatre","inst_name_lang":"en","place":"SP0054","start":"1953","source":"https://baike.baidu.com/item/%E6%B9%96%E5%8D%97%E7%9C%81%E6%AD%8C%E8%88%9E%E5%89%A7%E9%99%A2","created":"2018-11-06","created_by":"WH","last_modified":"2020-04-02","last_modified_by":"DP"},
{"inst_id":"AG0646","inst_name":"湖南省歌舞剧院","inst_name_lang":"zh","place":"SP0054","start":"1953","source":"https://baike.baidu.com/item/%E6%B9%96%E5%8D%97%E7%9C%81%E6%AD%8C%E8%88%9E%E5%89%A7%E9%99%A2","created":"2018-11-06","created_by":"WH","last_modified":"2020-04-02","last_modified_by":"DP"}
,
{"inst_id":"AG0647","inst_name":"Lu Xun Academy of Fine Arts","inst_name_lang":"en","place":"SP0024","start":"1938","source":"https://zh.wikipedia.org/wiki/%E9%AD%AF%E8%BF%85%E8%97%9D%E8%A1%93%E5%AD%B8%E9%99%A2","created":"2018-11-06","created_by":"WH","last_modified":"2020-04-02","last_modified_by":"DP"},
{"inst_id":"AG0647","inst_name":"鲁迅艺术学院","inst_name_lang":"zh","place":"SP0024","start":"1938","source":"https://zh.wikipedia.org/wiki/%E9%AD%AF%E8%BF%85%E8%97%9D%E8%A1%93%E5%AD%B8%E9%99%A2","created":"2018-11-06","created_by":"WH","last_modified":"2020-04-02","last_modified_by":"DP"}
,
{"inst_id":"AG0648","inst_name":"Shanghai Ballet Company","inst_name_lang":"en","place":"SP0006","start":"1966","source":"https://en.wikipedia.org/wiki/Shanghai_Ballet_Company","created":"2018-11-06","created_by":"WH","last_modified":"2020-04-02","last_modified_by":"DP"},
{"inst_id":"AG0648","inst_name":"上海芭蕾舞团","inst_name_lang":"zh","place":"SP0006","start":"1966","source":"https://en.wikipedia.org/wiki/Shanghai_Ballet_Company","created":"2018-11-06","created_by":"WH","last_modified":"2020-04-02","last_modified_by":"DP"}
,
{"inst_id":"AG0649","inst_name":"Chinese Academy of Social Sciences","inst_name_lang":"en","place":"SP0005","start":"1977","source":"https://zh.wikipedia.org/wiki/%E4%B8%AD%E5%9B%BD%E7%A4%BE%E4%BC%9A%E7%A7%91%E5%AD%A6%E9%99%A2","created":"2018-11-06","created_by":"WH","last_modified":"2020-04-02","last_modified_by":"DP"},
{"inst_id":"AG0649","inst_name":"中国社会科学院","inst_name_lang":"zh","place":"SP0005","start":"1977","source":"https://zh.wikipedia.org/wiki/%E4%B8%AD%E5%9B%BD%E7%A4%BE%E4%BC%9A%E7%A7%91%E5%AD%A6%E9%99%A2","created":"2018-11-06","created_by":"WH","last_modified":"2020-04-02","last_modified_by":"DP"}
,
{"inst_id":"AG0650","inst_name":"The Commercial Press","inst_name_lang":"en","place":"SP0006","start":"1897","source":"https://zh.wikipedia.org/wiki/%E5%95%86%E5%8A%A1%E5%8D%B0%E4%B9%A6%E9%A6%86","created":"2018-11-15","created_by":"WH","last_modified":"2020-04-02","last_modified_by":"DP"},
{"inst_id":"AG0650","inst_name":"商务印书馆","inst_name_lang":"zh","place":"SP0006","start":"1897","source":"https://zh.wikipedia.org/wiki/%E5%95%86%E5%8A%A1%E5%8D%B0%E4%B9%A6%E9%A6%86","created":"2018-11-15","created_by":"WH","last_modified":"2020-04-02","last_modified_by":"DP"}
,
{"inst_id":"AG0651","inst_name":"China Association for Science and Technology","inst_name_lang":"en","place":"SP0005","start":"1958","alt_start":"1958","alt_end":"1980","inst_alt_name":"People's Republic of China Science and Technology Association","source":"https://zh.wikipedia.org/wiki/%E4%B8%AD%E5%9B%BD%E7%A7%91%E5%AD%A6%E6%8A%80%E6%9C%AF%E5%8D%8F%E4%BC%9A","created":"2018-11-24","created_by":"WH","last_modified":"2020-04-02","last_modified_by":"DP"},
{"inst_id":"AG0651","inst_name":"中国科学技术协会","inst_name_lang":"zh","place":"SP0005","start":"1958","alt_start":"1958","alt_end":"1980","inst_alt_name":"中华人民共和国科学技术协会","source":"https://zh.wikipedia.org/wiki/%E4%B8%AD%E5%9B%BD%E7%A7%91%E5%AD%A6%E6%8A%80%E6%9C%AF%E5%8D%8F%E4%BC%9A","created":"2018-11-24","created_by":"WH","last_modified":"2020-04-02","last_modified_by":"DP"}
,
{"inst_id":"AG0652","inst_name":"China Artists Association","inst_name_lang":"en","place":"SP0005","start":"1949","source":"https://zh.wikipedia.org/wiki/%E4%B8%AD%E5%9C%8B%E7%BE%8E%E8%A1%93%E5%AE%B6%E5%8D%94%E6%9C%83","created":"2018-11-24","created_by":"WH","last_modified":"2020-04-02","last_modified_by":"DP"},
{"inst_id":"AG0652","inst_name":"中国美术家协会","inst_name_lang":"zh","place":"SP0005","start":"1949","source":"https://zh.wikipedia.org/wiki/%E4%B8%AD%E5%9C%8B%E7%BE%8E%E8%A1%93%E5%AE%B6%E5%8D%94%E6%9C%83","created":"2018-11-24","created_by":"WH","last_modified":"2020-04-02","last_modified_by":"DP"}
,
{"inst_id":"AG0653","inst_name":"People's Liberation Army of China","inst_name_lang":"en","place":"SP0005","start":"1927","alt_start":"1927","alt_end":"1949","inst_alt_name":"Chinese Workers’ and Peasants’ Revolutionary Army","source":"https://baike.baidu.com/item/%E4%B8%AD%E5%9B%BD%E4%BA%BA%E6%B0%91%E8%A7%A3%E6%94%BE%E5%86%9B","created":"2018-11-25","created_by":"WH","last_modified":"2020-04-02","last_modified_by":"DP"}
,
{"inst_id":"AG0653","inst_name":"中国人民解放军","inst_name_lang":"zh","place":"SP0005","start":"1927","alt_start":"1927","alt_end":"1949","inst_alt_name":"中国工农革命军","source":"https://baike.baidu.com/item/%E4%B8%AD%E5%9B%BD%E4%BA%BA%E6%B0%91%E8%A7%A3%E6%94%BE%E5%86%9B","created":"2018-11-25","created_by":"WH","last_modified":"2020-04-02","last_modified_by":"DP"}
,
{"inst_id":"AG0654","inst_name":"World Economic Research Institute","inst_name_lang":"en","place":"SP0006","start":"1964","alt_start":"1964","alt_end":"197x","inst_alt_name":"Fudan University Capitalist National Economic Research Institute","source":"http://www.fudan.edu.cn/entries/view/129/","created":"2019-06-15","created_by":"WH","last_modified":"2020-04-02","last_modified_by":"DP"},
{"inst_id":"AG0654","inst_name":"世界经济研究所","inst_name_lang":"zh","place":"SP0006","start":"1964","alt_start":"1964","alt_end":"197x","inst_alt_name":"复旦大学资本主义国家经济研究所","source":"http://www.fudan.edu.cn/entries/view/129/","created":"2019-06-15","created_by":"WH","last_modified":"2020-04-02","last_modified_by":"DP"}

]
